{"problem_name": "list_constant", "system_id": ["aleph"], "system_name": "aleph", "trial": 5, "solution": "magic_value([cbc,byv,blc,fy,bal,rr,ahn,cjm,coz,dtv,aui,ecz,dcg,ox,dbm,jf,aar,dul,en,bsf,emw,cqq,eeo,cyc,bfe,csk,bay,tg,co,bgq,zc,eio,erh,eaa,oj,etf,dnb,ehq,si,eee,dra,bjn,cya,ts,dmc,xi,chp,bjx,efo,ay,bum,emh,coh,btc,dti,awb,eto,ax,czn,dta,bhq,bst,dyq,aod,eq,elx,ur,can,dzk,bsp,chr,blt,asa,apt,di,cbx,cya,clg,bdb,cmq,bnx,xz,ut,ene,bjn,cgh,bft,etf,pf,j,lj,eds,ayw,cml,aqf,cpf,cjp,wx,ux,air,aer,cgx,ebn,csy,dje,abk,vp,ccl,mn,dix,epg,bf,ahf,yh,ayv,bfx,ciz,vt,va,bqf,agm,ag,evq,eff,bgg,cwe,vb,v,cuo,egn,cnk,adp,etz,bzc,cdw,dvz,azj,dgq,cly,lk,im,ti,bqv,cxq,cdf,enn,buy,bnx,ayd,can,yc,axa,bhd,aez,cfa,bqn,bfi,agg,np,ewe,ic,pp,cwj,coc,brf,qc,beb,bjm,afc,dql,dni,cbc,coz,ehm,eoy,ahx,cfu,aje,bsn,eoj,cdu,btb,emu,avd,eim,byr,awz,xx,dej,elv,bsw,agm,fx,emo,hs,ehv,cnu,bqw,bno,anp,apw,dav,bzi,azq,anm,dyr,cq,aoo,is,bbm,esy,cfo,ayd,bwi,cuh,dpx,dsf,cno,rk,bvt,cst,fy,bcp,clb,cgs,dp,dor,esd,ejc,eoh,eew,jm,bcv,ahs,enx,yc,bsd,ctl,chw,agi,cvn,cq,ebg,ana,asa,dap,eim,end,dqo,cyd,bvz,bgg,ayj,djq,dmx,bce,bij,bup,bmh,bqv,cjn,buw,dja,dcg,yj,aox,clo,zi,ddp,edo,ne,cht,ehs,dsz,etz,cpj,ckh,dxp,dwj,bqd,bsu,akt,caf,age,bnj,bnu,bjh,azc,epu,duk,dhh,dp,ehf,eoy,aoq,dqv,ack,qq,aqv,bge,bog,eky,bmv,eaw,ekg,cwz,cex,axl,cbd,etc,elk,fb,baf,eac,cpp,cma,bdc,boy,bwl,ecv,btq,bsf,jy,edq,ekq,ewb,eez,aty,aji,dpo,azm,ere,cbp,cwq,apn,apq,pw,dlf,aez,bms,te,qa,tg,awj,cbx,djr,c7,amx,ewp,bro,dtb,djl,re,dyp,czu,ect,i,ja,crg,aqa,tx,bth,enr,asw,bwr,dyt,cog,ajq,mz,enl,aqh,fk,df,eik,akt,zh,ere,eqs,bkp,bgm,bzf,avu,dop,ddz,rt,afr,ebj,dwt,byu,ama,cit,azy,dez,eie,evn,amm,ebu,cea,bam,bai,bpj,dla,amw,ehj,aca,cpg,bth,abg,doi,dqi,arw,hg,kk,bjh,bmu,euq,cbb,bga,doj,cze,cux,dik,ctd,cqp,aof,dhr,cyv,bgw,cai,aue,dfd,bdp,dat,crt,vr,ejo,aus,bnb,crn,qr,eas,enr,bky,efo,rb,amk,esz,bfc,esk,efz,cqd,azs,cdc,dxe,cvo,bza,den,cql,rp,aio,dwe,cng,anv,aqg,dxl,brt,ehy,qn,ciw,cya,cjw,dei,ln,agm,amp,bjs,dbq,cxw,aru,bgt,ejd,adz,bya,cqo,cnd,bu,bbi,cvz,dit,dwr,eog,bsz,bzs,dvf,vf,cty,fe,zs,evu,cnx]).\nmagic_value([equ,cii,eft,ejv,ccc,cni,ddy,bzy,aju,cfx,dci,uh,epw,bxu,of,cwd,dop,bsp,blr,ajc,cbx,c,etl,dup,dtz,dnk,eob,cyw,ehh,aso,ye,ass,bzo,alb,cq,csf,clq,bqf,bki,dtk,dfc,cjm,avr,tr,bpm,aki,eee,cqs,cvz,km,boj,anm,doc,ajo,bln,aba,cmm,ddw,dsy,ie,we,eea,cvh,crb,dja,li,box,beq,bbc,azg,aun,afy,oz,lw,bve,bso,btb,dyr,tf,dna,pm,aw,evs,brl,k,ecq,efa,vs,lb,bvx,dts,bt,ctn,eji,cak,amz,bfi,dh,ble,bha,beb,blp,dfi,bws,aeb,chb,ehx,bzm,bjb,bzg,buw,dli,afz,uf,aaw,bfc,efw,cxo,aof,euj,bps,alr,cgk,evx,km,xe,acl,qy,duc,csd,bwl,blb,bui,cck,agi,dra,zt,pf,sr,ayz,aw,dqe,aje,cye,awb,csr,bsi,aqj,bra,dmx,ciz,akq,cnh,end,egm,dhq,chh,bhy,bwt,ewl,ery,eao,aiu,pn,sq,edn,dzr,eiw,adz,dio,bhk,aqs,dbh,any,egx,ckp,eam,dhu,ar,dru,dwe,nf,dmj,ayr,esv,eps,brg,eia,dyi,aox,cni,cmb,dne,egf,dxh,ecj,dak,tu,bmu,cht,eu,ere,bxt,dag,cqe,cbu,eeq,app,eup,agy,bnm,brp,erq,dvo,dll,azd,dqa,ejy,egz,ju,cqx,byb,dtu,eay,cuu,bmr,csf,we,ajv,dnv,dil,bvr,c7,edv,gz,qm,aac,dnk,bbv,cku,jd,cbo,aos,afx,ahn,dzs,bpt,dfm,ub,ut,cht,bfp,cgb,euk,auq,bpf,dfl,dxx,tp,bqe,awe,xu,zr,bdb,ejp,qf,bte,dpw,dvy,eaq,gy,asf,dyp,cfr,emo,cbx,qh,eew,aeq,djw,asp,ais,bts,bsu,axd,art,mt,due,abh,ahm,ekt,bjz,bpz,buk,edo,amm,bbp,epu,ces,bbu,aty,er,elr,afb,gq,cha,arv,axt,abv,ya,yr,enp,eqf,cf,bku,nm,ekn,avq,ekr,bff,ajt,cgx,ym,emx,eqg,aeu,ne,fy,dei,avk,cum,aaa,ehl,nr,dav,ary,biq,ekb,kq,deb,aak,dvc,dmj,edw,dww,clh,bln,aii,bpa,cpw,bng,bhg,bfc,cuh,efe,ahx,eeh,dm,dvq,en,abr,dcg,cem,bxk,abl,ehz,bpz,cij,ia,bih,jr,aly,cxh,crp,dzo,uz,bmg,bes,ko,btu,bhr,aha,bpq,alx,bp,ari,clc,tf,cs,csg,ccu,dte,aj,dye,cfz,dyw,lw,acp,eoe,eiy,asw,arm,buq,lc,bnw,agr,dzi,mv,adi,bir,bov,dsg,dda,byn,acj,bhi,dsr,ahg,cot,bnt,bpk,bw,dtr,bdq,dbu,ejn,al,mq,eu,dks,edq,efc,ebx,ahc,daj,ecm,cms,axp,ii,bsm,dbl,cse,ber,etb,cvq,bus,bzz,aam,dcp,duc,clk,anq,dlt,dax,bh,amn,jx,eqr,atb,bgh,cwc,dnw,dpa,aps,crc,caz,eir,cxd,dzx,aka,afk,axx,hn,czd,rz,dpy,ege,brb,abs,efl,uh,dmm,dkb,apm,bnl,bja,bqm,cxs,eml,xd,akf,dju,cj,cpq,csn,akz,bra,cjp,bfq,qp]).\nmagic_value([dhq,eoy,esn,tr,dqu,dws,ala,deo,chx,bvq,dew,bre,dfo,aww,apu,bnj,chl,efp,bxo,ekm,chg,dva,cuq,avl,euv,cdo,cof,afx,ecn,aby,azy,zd,ebd,due,dea,ejs,cxm,blg,bxa,emw,rl,cjv,dnd,vo,agq,cpx,vg,ddd,dz,ai,cpq,afi,ceg,alz,nc,xl,dyc,cuq,aho,afl,lq,bvr,avd,bxn,blu,dqp,eru,etj,eam,cgb,fq,dkj,efq,dvy,dxi,eki,ho,epq,c7,efh,den,bgf,bmc,buz,bzt,drx,djl,dwy,ehs,ws,dem,dsa,bji,mg,esd,dcr,dvi,cas,bkq,ci,ewm,enq,dwa,awx,dni,cvq,bja,bsg,dbz,aed,sm,azn,bcq,aji,ali,epa,ciw,cij,beh,cmg,ajr,dad,rp,bfo,bac,edf,cux,bor,dkt,d,bev,dol,ehc,bjk,ary,drg,pd,sk,dmw,wu,dyr,cn,apn,ix,jq,dum,eoe,blu,f,tu,zn,cwa,ajp,ckm,h,eai,ahz,dyx,axo,apy,dss,aha,dyw,dof,qn,ewb,dzo,ash,xc,zz,bwd,cog,alz,dam,awk,ay,esy,dag,dvd,el,eti,cyc,gh,aga,cbr,clp,py,azt,um,tn,egf,ctz,asu,elg,cvi,eqq,ph,bcm,ava,avi,dwa,cgl,cqe,bit,bpm,ckw,dwe,bwn,g,clh,cdi,djl,caf,eew,rd,djp,dhj,gn,bgb,acg,bmy,byg,eat,dww,dhq,dcr,ms,btt,ekl,eup,cuq,cik,ern,bmr,bwg,czk,crx,xg,clf,cay,esw,djt,cir,erg,cni,bzz,atu,cby,ewl,cnc,ke,ems,dlg,cej,eis,cmz,elf,du,dkj,dvc,dqf,crl,elq,cjb,eel,bhw,cyv,ctn,pb,aha,e,et,qj,cph,cll,azh,cpe,blf,ed,awz,did,bkd,esm,ewa,bup,cnb,ell,egu,etd,hx,aax,clk,ejp,ww,eaa,bpd,cgr,bly,bbc,biv,abv,cub,xl,acq,ebu,drt,drt,bhw,rh,dwc,dnm,awt,eal,ccg,dc,aqb,mm,bnl,dis,ese,dxd,bqv,xb,aan,ewq,enm,cig,bqa,eam,cil,dsl,duz,uf,dom,wh,bce,ebr,cwz,oa,ml,vq,eed,bbw,eod,czk,akt,alj,cen,die,acf,ajj,axh,drm,auz,drc,yq,css,lv,ti,dqo,cej,apr,bny,eau,eei,btb,dup,eeq,axq,rw,eiv,ze,ht,dhf,evj,cmu,ahu,awg,dbl,ejz,bpu,dct,bhf,euq,dxy,btg,eue,dwd,avn,ays,bfv,agu,aqb,gh,dtq,cgh,eii,doy,dhw,dos,cqt,azf,hb,aan,cma,brn,beu,emf,asg,dpz,cac,esx,bvy,bdi,afd,cbj,ahd,eau,apv,akj,amy,byh,agr,dkw,sx,za,czs,cdk,nw,dmr,xw,dhw,egf,ecd,coz,emb,wn,eok,cz,dqv,bqy,azc,rr,euy,coa,cuh,eem,ass,eov,bdt,chr,eha,sf,wa,gc,l,ajp,cig,bxp,bux,ecf,djx,bfd,pc,dql,azr,bby,ces,cwf,bnb,dsj,duo,cqo,bzp,ahl,crz,aay,xg,adj,ceq,bx,env,aqs,afv,er,cel,bln,ajw,dcu,cpy,avp,cbo,cfl,dni,bl,etl,apv,cbu,ahp,drg]).\nmagic_value([dvp,ea,ajs,dq,cc,aun,qi,yn,z,amj,evw,dur,bea,dnr,ri,dpz,awh,cgp,bop,cpn,amm,byg,adq,bmt,egv,bod,epn,cd,ccp,qb,drn,ebt,bly,evx,eiz,bcr,eef,ai,eqw,bmc,abc,ets,cqe,dkr,bsk,zb,acq,anl,cqz,tc,mw,ear,cpt,crm,ebq,dvg,eqq,dkv,dfb,eqx,evj,hu,bjq,boi,buq,bpu,abb,bbo,abq,abw,epr,cbr,csb,asv,cyv,eph,k,csf,bfg,nt,ko,dhv,edu,aiz,axg,aal,dth,ehg,ka,km,dtm,apv,abd,ce,aci,cgx,bhp,dcf,epa,anc,blj,ub,cbc,ix,aqy,dsx,bt,dkj,xs,cnf,bqt,abf,dlx,bgc,cza,ib,cgm,bxv,cju,hw,eod,bso,chm,cqn,ept,afs,bsu,dlt,dyl,ddf,c7,dqe,mi,di,cnx,dbd,rz,bxl,egb,bvm,btf,cfv,ebr,bdc,dvd,ya,ehc,anj,bbd,qd,aet,del,abj,azf,cfb,dwv,bwa,dkx,ewr,aos,ehe,dqx,ccg,anu,aah,bsn,dcl,akc,ss,ko,at,bpk,oz,dkf,ke,aaa,aiu,dhg,bue,chm,bkp,bgr,ctx,yf,dzd,aqk,an,bbv,etb,ayz,aei,id,eof,ewj,aqb,pj,dkx,cii,rh,eck,gx,dhs,bx,bek,chs,rf,cnb,egu,axr,asu,ejh,dbv,ana,evu,bjn,clc,po,eqx,dmi,dgg,bpq,edm,bug,arh,arw,iq,ect,cxe,cpk,bud,diz,arn,ke,dns,enu,h,bny,dcz,blz,ctq,dqo,cwb,ebx,ekq,bwg,cda,ctw,apr,dva,cdg,apw,axx,cia,cee,dui,cir,aeg,rn,bmr,cdi,agr,bkl,dwd,dxz,ms,emv,dll,anc,cde,bgf,cyx,cwg,adi,brz,ctx,adx,ss,bdi,chb,cfo,bhw,eir,ekh,cts,cvn,vd,aec,bbg,cwc,akx,ahb,jp,cxu,dpk,aex,dfb,dta,ene,vj,zq,cdl,bny,eaf,duv,clx,tf,ai,bat,atl,jg,ear,das,eha,dpo,ayk,chd,czz,aqn,bgq,auk,buh,ew,qa,eug,edw,dro,cvx,chs,efc,yc,dzw,ry,cwy,qd,drs,evu,dtk,ava,ecb,btj,dhd,dto,wf,bml,xr,bdh,ees,cpv,djm,ap,bli,cmf,eh,bgd,akx,tw,bbf,tr,dxs,aom,euj,adx,jv,gk,dtm,pq,cge,czk,ajt,djp,ph,arh,csp,eot,bde,zz,dif,cxa,im,afz,bhl,cpi,sq,cbi,bbn,aqk,rb,ef,cls,bqp,btf,dec,cep,aih,awa,crr,vg,aau,acz,esk,eun,dit,dyw,czx,bvu,ehy,hh,bka,bld,eaq,eck,dqt,ama,amf,ehh,eig,aex,dvw,cnf,bhn,bxb,bkw,dqm,duw,bnw,cdt,ku,cbh,avp,qz,ehg,afm,bil,aqm,cte,drd,bjr,dmp,cur,bvu,ema,bky,hf,byy,eqr,dmd,bfo,dis,boe,ejp,dcw,evc,bgp,ahj,bem,xq,bam,bsq,akk,yy,cgv,dkn,dvu,aoc,ejh,bxa,esf,ru,bew,aby,cua,afj,dce,ceu,afx,dgq,chs,bdd,eay,bhv,nj,dil,eba,boy,aiv,ask,com,dfv,are,emr,vp,fx,czy,blm,ro,ala,ctv,dnl,buf,bft]).\nmagic_value([yy,ckx,bzz,bas,dmr,axm,ckx,boy,cvk,hg,cgs,ecu,eaf,bwx,cxg,dqp,cdl,tz,deh,beh,bbn,boj,cyf,ebx,jk,abr,bwt,bgf,ari,euk,dsz,dvc,dly,epu,acm,dga,ahh,kz,aps,cpj,qf,bqs,apw,abw,epq,mu,erc,bei,pg,bnq,dij,cow,bpr,bsv,dds,ato,bkf,bgv,asp,ad,bpm,atv,alm,bws,dcz,deu,eoo,xu,axo,aqf,mi,dvh,ema,dsm,bft,clu,brc,box,bwq,bro,cnr,ber,efm,ch,aci,bnv,doy,bmh,cwn,asv,rd,ceb,nm,euo,ets,dkm,dri,hk,dij,zw,avx,egj,dzf,ajn,cos,bwn,cgz,pa,ems,esl,dqf,btv,aza,eev,daz,ewl,duf,csa,ehv,ed,cgk,bkd,aac,emq,if,ayr,csm,dsx,az,ash,czr,cnf,cem,cuu,bkj,enq,yt,aqp,bok,agy,ccb,aln,enk,bsv,enx,bbi,cmh,bqd,kv,bbd,emz,vt,esf,civ,y,aha,cue,o,bum,rc,cvf,q,axd,bwc,ceh,kc,aye,axq,eoa,ddr,bxb,bpm,ewc,ctg,wn,bws,dzv,evr,bwz,ddl,sr,cly,abo,eou,alf,cau,acb,dyy,drs,ben,bvs,avo,xv,czl,hq,eqw,hx,nt,qo,bd,f,g,bej,avg,bj,ve,csh,te,crn,np,cbq,cbb,dts,pl,eco,dja,ccm,tp,dnf,bsm,aox,bqz,arf,cpb,ena,cik,aop,ejs,ecg,zo,dnd,ip,bwq,eae,aum,brb,aix,cgz,acd,ani,ki,eua,alf,ckd,cfq,bqv,dto,aqv,qi,aym,xl,sf,ean,dnl,ekg,cps,cwk,bcx,cht,aao,csf,dvg,bsr,dtd,diw,kj,etx,dvx,dnm,bew,aqb,cxg,bpf,dvf,duz,cez,boz,bss,bi,mw,ejj,bqg,asg,chq,zs,bui,cqe,rb,dvf,emw,cko,bwg,dlz,awa,dah,xa,ewe,cid,bxm,cpd,euf,bjp,arx,yw,dxt,pu,dab,etv,cbm,dno,eai,egy,bix,cku,bmg,bwm,acq,cvm,bt,bcv,aqw,tv,dnq,amu,bd,drp,dpp,brc,sk,esj,dxp,dyv,asx,bwr,cya,dji,bvr,euh,yk,ym,gv,ayt,cii,clm,bvs,dwn,dbg,egs,nd,egh,bhd,jl,bsh,bum,csx,aop,dkr,btx,axe,in,ajc,clr,bei,ayb,cis,cxr,ece,acp,c7,caw,bep,cye,jm,eab,dbh,bfw,cdc,ddo,bqc,gu,ewe,bet,ed,axt,eof,aak,cxh,dqj,fe,egv,bwp,aih,chl,atz,eja,cbj,xq,car,la,bjp,dlu,alu,ask,cao,pf,cyu,czz,dzg,bzh,aaf,zd,brr,acm,cei,vs,cci,dxr,cqs,bme,ok,bfc,cfi,jb,dbs,alc,brv,tw,iw,crp,czv,xn,eht,cle,eoj,cdi,rh,aij,eqe,csc,bgc,bcc,oz,hh,bzw,apf,awe,bxj,box,bhk,agk,dkl,bhe,dba,ars,ags,axy,byt,cva,cru,dtd,ejp,cxp,dxl,akm,cgc,crb,wn,euq,etb,abz,dji,dwb,arj,avw,dnw,ik,eko,ayu,etp,efb,fy,dqt,ced,azd,cxq,awa,chr,diq,cls,gu,eqc,awl,akc,cbj,pi,cpy,aco,dde,dje,chq]).\nmagic_value([dps,ekq,eoa,cii,cwc,cnj,buw,czf,dx,dfs,ccs,aou,eac,ebx,aer,cxg,xg,ejp,dmu,eud,enn,axv,dns,drs,ewn,apr,bqq,ebr,zt,eb,cab,dow,t,bdp,adc,cng,egn,apm,kj,dse,cbr,ddm,ddy,czz,alj,cp,bfz,ddz,bbz,dol,dz,amf,bwz,ewl,bgf,epr,ddb,uv,bsh,adh,c7,cst,bx,eam,bjc,dgq,dqj,bey,ekk,enh,amm,ux,bfr,con,aru,dqe,aos,bld,azi,ar,duu,bfl,amy,um,jo,abm,esg,ajn,bbh,amq,cqd,afd,ebs,cqu,ei,ebr,ewc,dfp,om,auy,cmm,alo,cgl,cqq,dny,esp,crg,bqa,bli,elz,bjh,ark,acy,bfu,ai,cvs,dgu,ewd,btn,bti,evz,dep,bel,adh,egw,eqx,dym,ens,dwj,nx,bms,cjh,mk,bqe,zt,cnk,cie,sv,cht,cxy,efn,ym,epu,qm,avz,awl,xc,dtq,dae,eow,tr,ehj,dvo,aln,gq,cuu,iv,agq,nz,eoe,ega,zk,vo,dtv,lt,qv,aky,ctv,dhn,crv,bey,dza,avd,een,brw,ejc,hl,cyj,crd,axh,ar,bxe,bwo,ber,cpx,cdr,elp,eiz,anj,chy,nh,rb,bag,cgn,cvz,eae,coq,gu,aic,cpf,wn,egm,ey,bdi,md,civ,lj,dws,ajt,ki,clx,day,bzr,avr,anr,cvb,era,bgo,dai,bhv,bat,cpt,rv,kg,clt,atq,anc,dfd,dxq,agv,bzq,eml,od,cyr,etq,ekm,cll,csn,yo,dxy,bfb,aup,cew,ekt,abz,chf,bim,bic,bzz,aa,jb,dij,zi,efc,aoo,dyo,ebk,chw,blt,dpv,up,cmb,cgz,evo,eqh,cmo,cza,ajf,cpm,bnu,cjw,dwu,dnf,egt,dcw,dop,ekv,ara,ekx,bzx,dqz,dsc,asp,brf,cgh,kg,ddu,dxn,ss,doz,dqs,edw,ajn,mm,ajh,egq,ewl,ebh,cvt,cbj,azk,bbz,egu,uu,dfr,enj,dgb,fk,euo,cud,dua,ayi,b,cct,era,ceh,xh,aer,cmm,ddq,xo,ddf,dpa,dpf,dcm,boe,erh,bwu,eob,aiy,esa,ciz,dvd,uc,eqh,eft,ejs,buk,dxr,kw,ciq,euc,aqv,vh,crl,bdt,epv,ue,akv,ejp,tt,dcs,dnk,cmu,clr,eqn,bwx,ehk,euf,dwu,bti,bgc,ll,ux,azv,aen,dcs,elz,ctc,eue,my,wo,dxm,cnl,axg,dal,amd,dle,dug,agm,dam,cai,acc,bb,zo,ehf,mq,ms,csj,bbs,wc,ou,dgf,eou,div,acl,dgw,bhx,bgh,bdt,ctu,drx,dlv,bso,egz,djq,efz,csv,djo,ahs,cua,dji,yi,aaf,bzz,ewz,dzf,dgi,bs,del,ads,dix,efg,kr,aeh,ecc,ge,tv,ebr,bwh,cvd,crr,cdx,mk,ayf,bpc,fy,cjp,awm,lj,ais,bcr,cqm,erd,czg,edb,crk,afu,cyp,aya,btq,nd,cat,ccu,qa,dif,biu,bwt,elu,cud,bsr,cds,cff,bgv,epf,ang,ahu,alh,dwu,byg,bfe,dqy,bkc,epy,bur,doj,ejr,enu,ewd,bcv,bqm,et,zu,ayj,xp,cxn,crr,duy,qc,eor,adt,cyx,ciw,ayr,ebc,by,die,asa,efs,ayd]).\nmagic_value([bfo,dxg,aop,cte,by,crt,dun,yj,egw,cci,bup,ejm,ahk,bos,dcz,bfi,dzq,ayj,eus,bcs,acr,dzm,epw,na,ccw,bbr,dw,cav,aaf,ajy,col,afp,agi,ba,apn,doj,cvd,ccb,ahv,eus,dil,yv,ays,egv,akg,wg,cpg,nq,cgt,ejo,dnh,bzu,ckx,coy,dfy,kp,efx,ckf,ecm,aso,uh,ee,eoi,eia,dyl,cim,eao,adb,bdz,cou,abd,ef,czi,dxy,dcm,eor,dsk,bnq,aeo,ebl,avr,cxb,th,ddj,dch,aqc,cya,dvi,bbp,ers,di,epo,bbp,dqi,epl,def,dhw,chk,bre,cnl,ecw,bex,dux,agp,bht,dxj,hk,le,boa,bbs,afq,bxx,dzz,auw,enr,ns,dgz,axn,ho,bgc,deg,qh,apo,bor,y,acj,dmg,aqo,h,ekm,dvt,cqn,dsg,awn,dav,dac,avo,eqx,dlj,dky,dck,eao,cq,bcm,bhr,eu,efw,cyc,egv,bgm,elu,djg,ad,dor,ot,des,cxc,boh,bmu,bsk,ekq,aaq,oe,hi,emh,auj,azq,ayk,c,ccp,arx,boy,u,dqv,ef,ctp,vb,cjg,aif,aia,clq,dgl,aaz,ld,ano,euq,adk,vu,bai,dw,ajo,azh,aqx,cyk,za,dwq,ckh,ll,csg,cnc,br,eln,ehc,eed,eix,aqx,mc,byh,eht,chi,dgv,kj,bld,dnq,by,bqq,aws,adz,bha,dkz,eak,bfq,crk,eop,adf,ecz,csf,bxl,bdk,cpe,dmz,afy,dfw,eni,ehe,bcq,bkf,bjw,egt,bov,vx,dtj,ahs,z,cnq,eok,hr,bxo,etr,dxl,jv,wo,bcp,dee,dml,crr,esb,lz,cuv,cjl,cd,bad,dku,tc,daz,atk,ah,dxs,cui,cfa,dkh,dpz,abn,bul,xh,egh,cqt,aft,efk,bfj,cmf,alm,clj,evw,eff,amz,erc,vh,ebx,iz,cig,elf,erb,ev,anp,eof,ckz,eql,all,c7,cqx,if,axk,chb,aqe,dgr,eph,cip,ddk,afb,xp,dcz,xm,ain,ccs,bgh,btr,etn,eqv,lu,aru,dns,dn,coj,ayp,cet,cna,bj,cyy,bzy,eoc,ain,akq,ags,je,dlb,ead,akp,efc,bwb,cdz,ejj,dhy,bgw,esx,bor,dlp,dah,qx,eky,ckp,dlz,ekg,bip,evt,aoq,cx,cws,ns,dzc,att,caf,dem,hi,dqt,egj,aco,eey,adj,arg,afv,efz,ft,cnf,aqy,csf,cdk,dps,cph,er,eim,bam,bcz,cro,os,cdy,djj,awv,dnq,dal,bdq,aus,dbk,ene,ekj,eff,ess,dm,cqm,ejt,bad,bpt,cnm,cwd,a,bir,bkl,lt,eja,ajt,deb,bjl,epb,dme,dnz,dgx,eic,an,ama,ako,cfk,hz,bed,eao,amn,cnf,dsq,ckq,dyn,zm,cnq,anz,zk,dbw,amj,anv,dcs,esn,bsx,cfv,bhf,enc,et,efp,ys,bbn,dle,chm,ano,bda,brn,bjz,jz,wo,awf,ekc,dls,eqy,dfk,dhk,cit,xi,cma,mt,dbk,cgm,bpp,cte,dtb,cna,bwg,im,bc,adx,ett,aik,cwm,dne,ajs,cq,dl,mo,ag,vn,aev,yt,ln,alm,eew,cds,ajn,cgf,cue,gd,eqg,diq,eic,crm,afb,bnl]).\nmagic_value([crx,fi,bjb,eeg,dqp,dkn,alk,aat,nh,adm,dma,deu,ewz,aus,ehs,abp,bzk,bxv,ebq,etx,avi,dha,dvl,ehn,axq,qr,ajs,esn,iy,esp,dio,gz,dib,euo,dnf,cyy,cwg,cqx,akw,bnu,dll,qh,dpv,afd,abo,eor,ato,bqf,os,yn,evr,wy,bjt,ero,eop,cdx,ctk,bah,aa,dbu,dph,azl,amd,dwl,ciu,epk,boe,epw,clg,bls,acf,cwg,cit,epy,ahg,qj,czq,aqy,dfy,efr,aus,dyp,bts,cil,dxc,amj,cmg,dtd,cuw,dvq,kl,bjt,ctg,cxg,bhf,vg,w,axe,bif,clm,cle,bwu,vg,dmd,djs,af,doe,eeo,su,bwq,dxg,eoz,bjs,eoh,boz,ck,euo,ept,cjf,avo,bzq,dpb,bck,bht,enw,dsv,arl,pq,cwa,ctz,bsr,bcz,bdk,euu,xv,fo,epu,aaw,afs,bbq,cxo,cj,bcq,dak,eec,hv,bji,bsj,dqz,dtw,cyq,akc,coe,avq,dye,cml,dts,bdt,ud,dyv,q,bve,aiv,esu,cuq,cli,crf,cnp,cdx,dpv,cne,zd,ete,ewi,epc,dfo,diy,dpf,ddr,anr,azu,cup,eji,efw,buj,ctl,cav,vp,byh,doh,qu,bnc,crs,bnl,bmq,kk,enw,xc,abh,cxw,cqo,wt,nx,cdb,cbl,eol,bpg,xj,dvn,cnv,bkl,eby,bmg,cdw,ery,diu,cxo,dyl,sx,evi,ajg,bgo,efl,yd,anx,bvd,apc,cvr,cjm,dmw,bqx,ebt,agq,dny,fx,epz,bls,dja,ctu,bug,il,bkg,duh,ajh,eta,eis,aja,ayc,eu,brj,baw,tm,eah,eja,eds,cda,aee,ed,dqy,hx,cwm,ctb,asf,mr,bru,bdy,ery,ene,dnr,anu,bmv,bpa,crc,bse,bik,dkt,cwe,ayc,dwx,bpq,ctt,dol,ayy,cvv,pa,ayv,bzk,cer,sc,ra,arh,ahc,ebl,fk,ehn,bwz,aag,ane,ml,qv,bmz,eik,coa,cre,bkm,daw,enp,aba,eap,axw,el,djd,asj,bhn,amm,ss,ry,ddf,bgl,epl,azh,blh,eug,ajp,aji,dmr,bcs,cqx,beo,aeq,ecp,avt,axj,gt,atb,dvl,drf,cor,edw,vz,buw,emr,bfw,coo,cfk,apv,atg,awh,ede,egh,axm,ebn,axt,xw,gf,vm,c7,bqo,ajw,bit,ejv,bqn,cya,ahn,ckn,ecx,ch,dfo,cux,dpq,azx,elt,dvz,eio,bkl,aov,cfa,daq,abq,emt,bai,dit,uh,aac,bdr,dzq,bo,cxz,ana,eia,aos,bxz,ebh,cal,cae,del,che,cfe,csc,yr,btm,btp,aoy,dfp,erl,rw,auo,dzv,bus,dot,ceu,alm,eus,dzv,aex,ebc,cqr,bla,cgk,bv,ewr,dev,acu,bmc,hg,jc,ail,doq,ced,ces,gz,ed,deu,mn,erf,cnl,ewt,ewd,ke,bfa,ape,aft,btk,dep,ebg,ckp,ko,cu,dbq,epp,ekx,fj,awn,buu,mj,ecr,dai,qa,cno,eoq,btw,ayg,bfm,ell,dfm,cbr,cww,bpr,ape,bro,bmy,abl,bjp,din,cxu,euj,cxp,pe,cmy,bfw,cuf,blz,eod,bxv,dgu,dl,ega,brp,by,aqr,efy,ma,esv,ciq,dar,crx,ctd,bey,arc,bel]).\nmagic_value([bvc,cbo,egd,bnp,afx,ams,ly,bnt,deu,des,dct,cii,efp,edy,ajm,asy,cel,djs,cht,yd,bum,acl,bza,en,cou,bkm,cbt,fk,ajf,dmx,cxq,ckq,bey,lq,bes,car,bmp,crp,acr,mi,ekc,ahl,ajl,blr,bir,bqr,adt,bjt,gr,ckt,dzv,dxv,ayj,eiv,fm,etb,bkj,dmy,csw,atk,efs,cyf,bvu,jd,awr,dpi,cbz,aii,bcb,dwx,dlb,afp,cwh,ckm,c,dag,buu,etk,cye,bpy,cvm,bm,che,emg,dro,wi,hx,ccq,dvi,bru,evn,blh,jp,bgx,dro,cc,dfb,aea,alf,cim,bcd,dsb,eka,clr,amb,ash,ecy,dfl,ela,egh,vk,hm,bzi,bdl,bhx,bky,cyf,crl,emn,ecv,wx,ku,eat,bt,cot,dsg,dcz,bst,atq,dxu,dmg,avr,atu,dfg,akt,cwp,bqb,xw,cjc,bwx,cbt,ada,atm,cis,bau,dls,bub,din,cyh,cuo,eb,cmz,bjp,aaq,eeu,ty,afp,dyz,rw,eco,baw,bra,km,ip,djb,alh,baj,sd,czg,bwv,dah,dbf,bzk,coe,eqw,clp,ddo,ahy,bce,aph,ewt,ir,dfg,ccz,dmm,aah,c7,efy,cri,dwh,bll,emt,dhp,ajl,dzj,cah,cso,gl,bbg,ahc,ewc,dkh,dhk,dfz,dgd,blt,aoz,ais,ejd,ckt,azh,djd,dbp,alg,bux,cmo,cih,atx,anp,bxw,bsc,bco,egv,ert,dok,bgx,aft,lg,cqt,eca,efx,dje,bmc,pm,afh,dgr,ajw,clw,gm,alw,apd,ent,apo,l,cmm,akn,bmn,czl,bgg,os,sa,cne,afc,eqb,wx,csd,dup,qs,cxe,rq,auq,abv,dkz,el,cki,axk,dnn,brv,elv,dtq,bcy,zn,yl,dyr,eft,cls,cvv,im,ddl,dm,amu,aqq,cml,dhv,kx,aju,arp,axe,ago,dtu,cld,att,bcs,akv,efw,apd,aac,bva,cfz,dkd,ccv,dfd,bda,ajy,eev,cyi,eld,ayg,dgr,btt,du,dsx,cqi,eva,ctt,aid,bmv,hu,crt,ayo,epr,czj,bzk,avd,dhe,bgf,ejn,cjy,ail,equ,anx,bga,cle,bnf,dng,cwp,ci,bxq,eng,efw,dcb,bsu,aqg,beh,ki,dvs,eei,alf,dbc,bnz,deq,ed,aia,aos,bur,dmz,cxm,ddi,tj,efz,cmo,apc,dni,avs,aat,drf,ckh,drs,bwv,bxe,dqu,arb,bjq,fg,fc,qa,asb,cvd,esv,ecf,eir,tc,dfe,ayz,yv,aq,aar,eow,awe,bgp,ath,bpk,bbc,bdq,ro,ali,blw,dvk,emp,aah,eiy,aeg,ci,vq,eal,dgh,dnt,aey,bxt,des,cdz,cxc,drl,arc,zb,amu,cdy,awt,enx,cui,jq,cok,cqy,abb,cu,aks,eju,dwv,gs,ahx,wz,aqz,co,dlg,azw,aum,dmj,dqk,cxd,zq,le,djb,aqd,eak,dvi,ym,dcb,erk,cry,bnc,cfb,deb,dbx,ech,akp,byi,cou,cek,apn,atk,dbz,agr,duc,beo,brx,ehr,dg,die,drj,bjq,dpi,ewz,bpg,dal,aio,azh,axt,aue,yh,bdl,crc,dao,yl,dxj,eep,eku,vk,bfs,mn,aqt,aln,brm,dzh,la,ber,avv,cau,jw,euk,ekh]).\nmagic_value([ayt,dxr,up,dxw,erw,it,cvd,dhk,eha,eqs,cem,ela,des,aab,amz,ht,mq,bwe,djp,bce,dhe,bav,bxt,czz,dsh,cwp,byv,cob,a,dwo,bfi,bkr,dea,en,eox,ddn,vv,bwd,cvi,dii,eck,dvu,crb,dht,dye,cng,egr,bwj,cji,cun,ccg,axo,eli,dgx,epc,aor,cfz,bcn,dd,bgs,dad,cac,eii,ayu,gi,bvf,dxg,diy,apk,nb,ew,bsm,cyw,buh,crt,epn,bgh,akg,ym,bev,wt,aff,dww,ekn,bwc,bbx,drz,xt,dn,vt,agw,cmn,bty,bzf,bq,cwv,dnh,ars,dhq,dug,cnk,eps,bja,mg,ald,crh,axu,dmd,dn,mz,nq,duw,ar,tc,asu,mb,dak,bfe,ebr,bxd,eqf,euc,dni,bx,aed,ckr,ecd,ams,bvc,dwm,doq,atq,xa,cor,aps,bns,elr,akv,csi,arm,zi,ejg,dwr,dov,ln,bvs,aek,ry,nc,dqh,eap,dap,tn,zv,dxz,lf,bjk,ft,dkc,dtn,bev,aak,pd,bpc,dqr,ear,bop,aua,xt,dei,rl,bdi,ehd,cqm,dmy,evs,esw,dze,ddk,dqs,adf,aju,ale,in,epp,enw,jj,afd,erx,esc,cxl,egk,bks,zn,dsa,yy,dli,cre,atm,egd,egj,dkv,cnm,dui,che,sr,dhx,cra,bkp,aqt,eke,bxj,cr,dcs,sw,emh,efc,wd,clj,ac,bt,bxq,edb,dnx,cws,ahk,ddk,apz,ada,acl,cxg,aon,equ,avc,azl,dud,ewx,ajy,bsp,bnc,cvk,ase,dta,dxg,aej,yc,cbt,qg,cfn,afc,aem,yq,cyy,duw,azd,eqe,brg,dzt,dba,dgx,nn,csn,agq,qw,cd,epk,dhm,dah,bvw,dgy,bpu,pj,app,bmi,oi,enu,esf,elu,bml,dbi,sb,ctm,aqi,dcy,dwu,dgo,yi,dst,ag,cgz,dfz,apk,amv,avs,csb,bqv,dxw,dnk,cab,etr,dkn,asz,bvx,dqe,ccd,eju,dux,cmc,brh,dtf,equ,cwd,euu,xk,acm,cqf,bxx,dku,uy,iy,azu,bsq,bty,eka,col,eng,ekz,c7,brp,dmc,ie,cpd,ud,ava,etb,dzu,dbe,bau,eop,dmy,caz,djz,cdn,ayw,vc,efe,ewo,yg,cdc,bao,atz,oq,hh,cxv,lg,dmc,ckm,ete,ala,bfk,bmu,bpk,sv,chz,aua,djr,anb,emm,ejn,aoq,dsz,dik,chv,ebq,dtt,blh,bxu,ejh,aww,ih,jz,eor,dzs,aw,dwv,cei,aer,enm,bek,dla,dlf,bug,eei,bui,esq,cpk,kj,csx,djo,cfx,dez,cns,cjq,bbo,egt,ert,afe,bqc,duu,deo,bdl,emr,ckc,cvd,bzt,cgf,ul,buz,dql,aje,dzq,bfp,amk,aed,dee,bud,ckq,dcf,cpk,cnw,do,cuj,auz,aag,ch,ayc,bse,djy,cfm,bdx,cko,cjl,dt,cxz,dwy,buo,dlx,cbh,erb,ep,m,dg,bqn,efm,km,amc,bxe,clh,esc,eqz,aza,edw,abb,ewn,cep,cmd,byn,ake,alt,blh,dkr,dxk,bai,aiy,cyw,ehp,dco,aqg,yk,cir,akt,ept,drg,cbt,dwc,bxj,aez,eah,ehx,aqd,emh,br,ewu,tc,eoo,xc,enn,ehj,dzh,ebs]).\n", "total_exec_time": 64.488269917, "conf_matrix": [0, 1000, 1000, 0], "parameter": 4000, "__typ__": "ExperimentResult"}