{"problem_name": "iggp-buttons", "system_id": ["magicpopper_args"], "system_name": "popper", "trial": 6, "solution": "next(A,p):- does(A,robot,c),my_true(A,p),magic(robot),magic(p),magic(c).\nnext(A,r):- does(A,robot,b),my_true(A,r),magic(r),magic(robot),magic(b).\nnext(A,p):- not_my_true(A,p),does(A,robot,a),magic(a),magic(p),magic(robot).\nnext(A,q):- my_true(A,p),does(A,robot,b),magic(q),magic(b),magic(robot),magic(p).\nnext(A,p):- does(A,robot,b),my_true(A,q),magic(robot),magic(q),magic(b),magic(p).\nnext(A,r):- does(A,robot,a),my_true(A,r),magic(r),magic(robot),magic(a).\nnext(A,B):- my_succ(C,B),my_true(A,C).\nnext(A,q):- my_true(A,q),does(A,robot,a),magic(q),magic(robot),magic(a).\nnext(A,q):- does(A,robot,c),my_true(A,r),magic(c),magic(q),magic(r),magic(robot).\nnext(A,r):- my_true(A,q),does(A,robot,c),magic(c),magic(robot),magic(q),magic(r).", "total_exec_time": 2.2644044169999997, "conf_matrix": [27, 0, 113, 0], "parameter": null, "__typ__": "ExperimentResult"}