[{"problem_name": "multiple", "system_id": ["popper"], "system_name": "popper", "trial": 0, "solution": "multiple(A):- c8(A).\nmultiple(A):- c64(A).\nmultiple(A):- c512(A).\nmultiple(A):- c16(A).\nmultiple(A):- c128(A).\nmultiple(A):- c256(A).\nmultiple(A):- c32(A).", "total_exec_time": 13.043120625, "conf_matrix": [800, 200, 1000, 0], "parameter": null, "__typ__": "ExperimentResult"}, {"problem_name": "multiple", "system_id": ["popper"], "system_name": "popper", "trial": 1, "solution": "multiple(A):- c64(A).\nmultiple(A):- c256(A).\nmultiple(A):- c128(A).\nmultiple(A):- c16(A).\nmultiple(A):- c2(A).\nmultiple(A):- c32(A).", "total_exec_time": 13.294582042, "conf_matrix": [657, 343, 1000, 0], "parameter": null, "__typ__": "ExperimentResult"}, {"problem_name": "multiple", "system_id": ["popper"], "system_name": "popper", "trial": 2, "solution": "multiple(A):- c4(A).\nmultiple(A):- c128(A).\nmultiple(A):- c512(A).\nmultiple(A):- c2(A).\nmultiple(A):- c64(A).\nmultiple(A):- c32(A).\nmultiple(A):- c16(A).\nmultiple(A):- c8(A).", "total_exec_time": 13.00627175, "conf_matrix": [892, 108, 1000, 0], "parameter": null, "__typ__": "ExperimentResult"}, {"problem_name": "multiple", "system_id": ["popper"], "system_name": "popper", "trial": 3, "solution": "multiple(A):- c128(A).\nmultiple(A):- c4(A).\nmultiple(A):- c64(A).\nmultiple(A):- c512(A).\nmultiple(A):- c256(A).\nmultiple(A):- c8(A).\nmultiple(A):- c2(A).", "total_exec_time": 12.894082625, "conf_matrix": [773, 227, 1000, 0], "parameter": null, "__typ__": "ExperimentResult"}, {"problem_name": "multiple", "system_id": ["popper"], "system_name": "popper", "trial": 4, "solution": "multiple(A):- c2(A).\nmultiple(A):- c512(A).\nmultiple(A):- c32(A).\nmultiple(A):- c16(A).\nmultiple(A):- c64(A).", "total_exec_time": 14.119062333, "conf_matrix": [538, 462, 1000, 0], "parameter": null, "__typ__": "ExperimentResult"}, {"problem_name": "multiple", "system_id": ["popper"], "system_name": "popper", "trial": 5, "solution": "multiple(A):- c512(A).\nmultiple(A):- c16(A).\nmultiple(A):- c64(A).\nmultiple(A):- c256(A).\nmultiple(A):- c2(A).\nmultiple(A):- c4(A).\nmultiple(A):- c8(A).", "total_exec_time": 14.291422707999999, "conf_matrix": [754, 246, 1000, 0], "parameter": null, "__typ__": "ExperimentResult"}, {"problem_name": "multiple", "system_id": ["popper"], "system_name": "popper", "trial": 6, "solution": "multiple(A):- c2(A).\nmultiple(A):- c4(A).\nmultiple(A):- c8(A).\nmultiple(A):- c64(A).\nmultiple(A):- c16(A).\nmultiple(A):- c256(A).\nmultiple(A):- c512(A).", "total_exec_time": 14.087137250000001, "conf_matrix": [789, 211, 1000, 0], "parameter": null, "__typ__": "ExperimentResult"}, {"problem_name": "multiple", "system_id": ["popper"], "system_name": "popper", "trial": 7, "solution": "multiple(A):- c2(A).\nmultiple(A):- c16(A).\nmultiple(A):- c64(A).\nmultiple(A):- c4(A).\nmultiple(A):- c8(A).\nmultiple(A):- c128(A).", "total_exec_time": 14.190918083, "conf_matrix": [656, 344, 1000, 0], "parameter": null, "__typ__": "ExperimentResult"}, {"problem_name": "multiple", "system_id": ["popper"], "system_name": "popper", "trial": 8, "solution": "multiple(A):- c32(A).\nmultiple(A):- c2(A).\nmultiple(A):- c8(A).\nmultiple(A):- c64(A).\nmultiple(A):- c512(A).", "total_exec_time": 12.757207375, "conf_matrix": [545, 455, 1000, 0], "parameter": null, "__typ__": "ExperimentResult"}, {"problem_name": "multiple", "system_id": ["popper"], "system_name": "popper", "trial": 9, "solution": "multiple(A):- c128(A).\nmultiple(A):- c8(A).\nmultiple(A):- c256(A).\nmultiple(A):- c512(A).\nmultiple(A):- c64(A).\nmultiple(A):- c4(A).", "total_exec_time": 12.620946958, "conf_matrix": [664, 336, 1000, 0], "parameter": null, "__typ__": "ExperimentResult"}]